{"repo":"developmentseed/tipg","repo_stars":206,"repo_forks":36,"repo_createdAt":"2022-10-05T16:03:59Z","repo_updatedAt":"2026-04-28T08:45:52Z","repo_total_commits":737,"repo_url":"https://github.com/developmentseed/tipg","repo_description":"Simple and Fast Geospatial OGC Features and Tiles API for PostGIS.","repo_languages":"PLpgSQL,Python,HTML,Shell,Dockerfile","repo_watchers":8,"repo_open_issues":32,"repo_license":"MIT","repo_topics":"","repo_has_discussions":true,"repo_has_wiki":false,"repo_default_branch":"main","repo_archived":false,"repo_total_contributors":18,"repo_core_contributors":7,"repo_external_contributors":11,"repo_community_ratio":0.611}