{"repo":"pydata/xarray","repo_stars":4089,"repo_forks":1232,"repo_createdAt":"2013-09-30T17:21:10Z","repo_updatedAt":"2026-02-18T01:11:32Z","repo_total_commits":6360,"repo_url":"https://github.com/pydata/xarray","repo_description":"N-D labeled arrays and datasets in Python","repo_languages":"Python,CSS,HTML,Dockerfile","repo_watchers":101,"repo_open_issues":1336,"repo_license":"Apache-2.0","repo_topics":"python,netcdf,numpy,pandas,xarray,dask","repo_has_discussions":true,"repo_has_wiki":false,"repo_default_branch":"main","repo_archived":false,"repo_total_contributors":415,"repo_devseed_contributors":7,"repo_external_contributors":408,"repo_community_ratio":0.983}