{"repo":"hotosm/tasking-manager","repo_stars":568,"repo_forks":287,"repo_createdAt":"2017-02-02T14:31:35Z","repo_updatedAt":"2026-01-30T06:04:19Z","repo_total_commits":6475,"repo_url":"https://github.com/hotosm/tasking-manager","repo_description":"Tasking Manager - The tool to team up for mapping in OpenStreetMap","repo_languages":"Python,JavaScript,HCL,Jupyter Notebook,HTML,SCSS,Shell,Dockerfile,PLpgSQL,Makefile,CSS,Mako,PowerShell","repo_watchers":33,"repo_open_issues":441,"repo_license":"BSD-2-Clause","repo_topics":"openstreetmap,python,javascript,reactjs,postgresql,postgis,fastapi","repo_has_discussions":true,"repo_has_wiki":false,"repo_default_branch":"develop","repo_archived":false,"repo_total_contributors":115,"repo_devseed_contributors":3,"repo_external_contributors":112,"repo_community_ratio":0.974}