{"repo":"stac-utils/pystac","repo_stars":428,"repo_forks":129,"repo_createdAt":"2017-11-08T13:30:15Z","repo_updatedAt":"2026-01-29T18:12:17Z","repo_total_commits":2176,"repo_url":"https://github.com/stac-utils/pystac","repo_description":"Python library for working with any SpatioTemporal Asset Catalog (STAC)","repo_languages":"Python,Jinja,Shell","repo_watchers":23,"repo_open_issues":69,"repo_license":"NOASSERTION","repo_topics":"","repo_has_discussions":false,"repo_has_wiki":false,"repo_default_branch":"main","repo_archived":false}